sotabencheval/__init__.py
sotabencheval/utils.py
sotabencheval/version.py
sotabencheval/core/__init__.py
sotabencheval/core/cache.py
sotabencheval/core/evaluator.py
sotabencheval/image_classification/__init__.py
sotabencheval/image_classification/imagenet.py
sotabencheval/image_classification/utils.py
sotabencheval/language_modelling/__init__.py
sotabencheval/language_modelling/wikitext.py
sotabencheval/machine_translation/__init__.py
sotabencheval/machine_translation/languages.py
sotabencheval/machine_translation/metrics.py
sotabencheval/machine_translation/wmt.py
sotabencheval/natural_language_inference/__init__.py
sotabencheval/natural_language_inference/multinli.py
sotabencheval/object_detection/__init__.py
sotabencheval/object_detection/coco.py
sotabencheval/object_detection/coco_eval.py
sotabencheval/object_detection/utils.py
sotabencheval/question_answering/__init__.py
sotabencheval/question_answering/evaluate_v11.py
sotabencheval/question_answering/evaluate_v20.py
sotabencheval/question_answering/squad.py
sotabencheval/question_answering/utils.py
sotabencheval/semantic_segmentation/__init__.py
sotabencheval/semantic_segmentation/ade20k.py
sotabencheval/semantic_segmentation/pascalvoc.py
sotabencheval/semantic_segmentation/utils.py
sotabencheval-0.0.38.dist-info/LICENSE
sotabencheval-0.0.38.dist-info/METADATA
sotabencheval-0.0.38.dist-info/WHEEL
sotabencheval-0.0.38.dist-info/top_level.txt
sotabencheval-0.0.38.dist-info/RECORD
